{
  "persons": [
    {
      "name": "Arto Hellas",
      "number": "040-123456",
      "id": 1
    },
    {
      "name": "Ada Lovelace",
      "number": "39-44-5323523",
      "id": 2
    },
    {
      "name": "Dan Abramov",
      "number": "12-43-234345",
      "id": 3
    },
    {
      "name": "Mary Poppendieck",
      "number": "39-23-6423122",
      "id": 4
    },
    {
      "name": "Lilly Pipunen",
      "number": "050-9438576",
      "id": 8
    },
    {
      "name": "Amelie Gullynstein",
      "number": "040-8975674",
      "id": 9
    },
    {
      "name": "Bebo Vuener",
      "number": "050-5497483",
      "id": 10
    }
  ]
}